pygrpfe/__init__.py
pygrpfe/helpers.py
pygrpfe-0.1.2.dist-info/LICENSE
pygrpfe-0.1.2.dist-info/METADATA
pygrpfe-0.1.2.dist-info/WHEEL
pygrpfe-0.1.2.dist-info/top_level.txt
pygrpfe-0.1.2.dist-info/RECORD
