Metadata-Version: 2.1
Name: pygrpfe
Version: 0.1.2
Summary: Helper functions of Group Fixed Effect
Home-page: https://github.com/tlamadon/pygrpfe
Author: Thibaut Lamadon
Author-email: thibaut.lamadon@gmail.com
License: UNKNOWN
Project-URL: GitHub, https://github.com/tlamadon/pygrpfe
Platform: UNKNOWN
Classifier: Programming Language :: Python :: 3
Classifier: License :: OSI Approved :: MIT License
Classifier: Operating System :: OS Independent
Requires-Python: >=3.6
Requires-Dist: numpy
Requires-Dist: pandas
Requires-Dist: scipy
Requires-Dist: scikit-learn
Requires-Dist: statsmodels
Requires-Dist: torch
Requires-Dist: matplotlib
Requires-Dist: tqdm
